sphinxcontrib_beamer-0.0.2-py3.10-nspkg.pth
sphinxcontrib/beamer/__init__.py
sphinxcontrib/beamer/templates/beamer.tex_t
sphinxcontrib_beamer-0.0.2.dist-info/LICENSE
sphinxcontrib_beamer-0.0.2.dist-info/METADATA
sphinxcontrib_beamer-0.0.2.dist-info/WHEEL
sphinxcontrib_beamer-0.0.2.dist-info/namespace_packages.txt
sphinxcontrib_beamer-0.0.2.dist-info/top_level.txt
sphinxcontrib_beamer-0.0.2.dist-info/RECORD
