Metadata-Version: 2.1
Name: sphinxcontrib-beamer
Version: 0.0.2
Summary: Beamer extension for Sphinx
Home-page: https://github.com/ollehu/sphinxcontrib-beamer
Author: Olle Hynén Ulfsjöö
Author-email: ollehu@gmail.com
Classifier: Development Status :: 3 - Alpha
Classifier: Topic :: Documentation :: Sphinx
Classifier: Programming Language :: Python :: 3
Classifier: License :: OSI Approved :: MIT License
Classifier: Operating System :: OS Independent
Requires-Python: >=3.6
License-File: LICENSE
Requires-Dist: Sphinx
